README.md
setup.py
Blackforge.egg-info/PKG-INFO
Blackforge.egg-info/SOURCES.txt
Blackforge.egg-info/dependency_links.txt
Blackforge.egg-info/requires.txt
Blackforge.egg-info/top_level.txt
blackforge/AI.py
blackforge/__init__.py
blackforge/app.py
blackforge/asset.py
blackforge/entity.py
blackforge/events.py
blackforge/gfx.py
blackforge/globs.py
blackforge/input.py
blackforge/object.py
blackforge/resource.py
blackforge/utils.py
blackforge/version.py
blackforge/world.py
blackforge/assets/logo.png
blackforge/assets/logo5x.png