Metadata-Version: 2.1
Name: Blackforge
Version: 2024.1.18
Summary: Light Shines Brighter In The Dark.
Home-page: https://github.com/d34d0s/BlackForge
Author: Izaiyah Stokes
Author-email: d34d.dev@gmail.com
Classifier: Programming Language :: Python :: 3.12
Classifier: License :: OSI Approved :: MIT License
Classifier: Operating System :: OS Independent
Requires-Dist: Numpy
Requires-Dist: Pygame-CE
Requires-Dist: SetupTools
